cat_fact.py
main.py
routes.py
server.py
mseep_python_mcp-0.1.1.dist-info/METADATA
mseep_python_mcp-0.1.1.dist-info/WHEEL
mseep_python_mcp-0.1.1.dist-info/entry_points.txt
mseep_python_mcp-0.1.1.dist-info/top_level.txt
mseep_python_mcp-0.1.1.dist-info/RECORD
